chalice_cdk/__init__.py
chalice_cdk-0.1.0.dist-info/LICENSE
chalice_cdk-0.1.0.dist-info/WHEEL
chalice_cdk-0.1.0.dist-info/METADATA
chalice_cdk-0.1.0.dist-info/RECORD
